.pycheckrc
AUTHORS
CHANGELOG
LICENSE
MANIFEST.in
README.rst
ROADMAP
TODO
light.theme
sample-config
sample.theme
setup.py
windows.theme
bpdb/__init__.py
bpdb/__main__.py
bpdb/debugger.py
bphython.egg-info/PKG-INFO
bphython.egg-info/SOURCES.txt
bphython.egg-info/dependency_links.txt
bphython.egg-info/entry_points.txt
bphython.egg-info/requires.txt
bphython.egg-info/top_level.txt
bpython/__init__.py
bpython/_internal.py
bpython/_py3compat.py
bpython/args.py
bpython/autocomplete.py
bpython/cli.py
bpython/config.py
bpython/curtsies.py
bpython/formatter.py
bpython/gtk_.py
bpython/hy.py
bpython/importcompletion.py
bpython/inspection.py
bpython/keys.py
bpython/logo.png
bpython/pager.py
bpython/repl.py
bpython/urwid.py
bpython/curtsiesfrontend/__init__.py
bpython/curtsiesfrontend/coderunner.py
bpython/curtsiesfrontend/friendly.py
bpython/curtsiesfrontend/hycomplete.py
bpython/curtsiesfrontend/interaction.py
bpython/curtsiesfrontend/manual_readline.py
bpython/curtsiesfrontend/repl.py
bpython/curtsiesfrontend/replpainter.py
bpython/curtsiesfrontend/sitefix.py
bpython/test/__init__.py
bpython/test/test.config
bpython/test/test.theme
bpython/test/test_args.py
bpython/test/test_bpython.py
bpython/test/test_config.py
bpython/test/test_crashers.py
bpython/test/test_formatter.py
bpython/test/test_gtk_.py
bpython/test/test_importcompletion.py
bpython/test/test_inspection.py
bpython/test/test_keys.py
bpython/test/test_manual_readline.py
bpython/test/test_pager.py
bpython/test/test_repl.py
bpython/test/test_wizard.py
bpython/translations/__init__.py
bpython/translations/de/LC_MESSAGES/bpython.po
bpython/translations/es_ES/LC_MESSAGES/bpython.po
bpython/translations/it_IT/LC_MESSAGES/bpython.po
bpython/translations/nl_NL/LC_MESSAGES/bpython.po
data/bpython
data/bpython-gtk
data/bpython.desktop
doc/sphinx/source/authors.rst
doc/sphinx/source/bpaste.rst
doc/sphinx/source/bpdb.rst
doc/sphinx/source/changelog.rst
doc/sphinx/source/community.rst
doc/sphinx/source/conf.py
doc/sphinx/source/configuration-options.rst
doc/sphinx/source/configuration.rst
doc/sphinx/source/django.rst
doc/sphinx/source/index.rst
doc/sphinx/source/logo.png
doc/sphinx/source/man-bpython-config.rst
