Metadata-Version: 1.0
Name: bphython
Version: 0.0.2
Summary: Fancy Interface to the Python Interpreter
Home-page: http://www.bpython-interpreter.org/
Author: Tom Ballinger (but mostly Bob Farrell, Andreas Stuehrk et al.)
Author-email: thomasballinger@gmail.com
License: MIT/X
Platform: UNKNOWN
